Metadata-Version: 1.1
Name: test-packaging
Version: 0.1.6
Summary: Test of packaging.
Home-page: http://github.com/hector-mao-net/test_packaging
Author: Hector Mao
Author-email: hectormao1025@gmail.com
License: MIT
Platform: UNKNOWN
Classifier: Development Status :: 3 - Alpha
Classifier: License :: OSI Approved :: MIT License
Classifier: Programming Language :: Python :: 3.6
Classifier: Topic :: Text Processing :: General
